githubfetch/__init__.py
githubfetch/githubfetch.py
githubfetch-1.0.5.dist-info/METADATA
githubfetch-1.0.5.dist-info/WHEEL
githubfetch-1.0.5.dist-info/entry_points.txt
githubfetch-1.0.5.dist-info/top_level.txt
githubfetch-1.0.5.dist-info/RECORD
