Metadata-Version: 2.4
Name: githubfetch
Version: 1.0.5
Summary: Terminal-based GitHub profile viewer
Home-page: https://github.com/shubhpsd/githubfetch
Author: Shubham Prasad
Author-email: shubhampsd@tuta.io
Classifier: Programming Language :: Python :: 3
Classifier: Operating System :: OS Independent
Requires-Python: >=3.6
Requires-Dist: requests
Requires-Dist: pillow
Requires-Dist: imgcat
Dynamic: author
Dynamic: author-email
Dynamic: classifier
Dynamic: description
Dynamic: description-content-type
Dynamic: home-page
Dynamic: requires-dist
Dynamic: requires-python
Dynamic: summary
